{
  "store_id": "ST1076",
  "store_name": "Purplle_Mumbai_1076",
  "city": "Mumbai",
  "business_date": "2026-03-08",
  "cameras": {
    "CAM1": {
      "camera_id": "CAM1",
      "clip_start_utc": "2026-03-08T18:10:00Z",
      "detector_scale": 0.5,
      "min_motion_area": 2200,
      "entry_zone": "ENTRY_THRESHOLD",
      "entry_trigger_zones": ["ENTRY_THRESHOLD"],
      "exit_zone": "EXIT_THRESHOLD",
      "zones": [
        {"zone_id": "ENTRY_THRESHOLD", "polygon": [[0, 0], [960, 0], [960, 540], [0, 540]]},
        {"zone_id": "EXIT_THRESHOLD", "polygon": [[960, 0], [1920, 0], [1920, 1080], [960, 1080]]}
      ]
    },
    "CAM2": {
      "camera_id": "CAM2",
      "clip_start_utc": "2026-03-08T18:10:00Z",
      "detector_scale": 0.5,
      "min_motion_area": 2200,
      "zones": [
        {"zone_id": "PURPLLE_MUM_1076_Z01", "polygon": [[0, 0], [960, 0], [960, 1080], [0, 1080]]}
      ]
    },
    "CAM3": {
      "camera_id": "CAM3",
      "clip_start_utc": "2026-03-08T18:10:00Z",
      "detector_scale": 0.5,
      "min_motion_area": 2200,
      "zones": [
        {"zone_id": "PURPLLE_MUM_1076_Z02", "polygon": [[0, 0], [960, 0], [960, 1080], [0, 1080]]}
      ]
    },
    "CAM4": {
      "camera_id": "CAM4",
      "clip_start_utc": "2026-03-08T18:10:00Z",
      "detector_scale": 0.5,
      "min_motion_area": 2200,
      "zones": [
        {"zone_id": "PURPLLE_MUM_1076_Z03", "polygon": [[0, 0], [960, 0], [960, 1080], [0, 1080]]}
      ]
    },
    "PURPLLE_MUM_1076_CAM6": {
      "camera_id": "PURPLLE_MUM_1076_CAM6",
      "clip_start_utc": "2026-03-08T18:10:00Z",
      "detector_scale": 0.5,
      "min_motion_area": 2200,
      "billing_zones": ["PURPLLE_MUM_1076_Z_BILLING_01"],
      "zones": [
        {"zone_id": "PURPLLE_MUM_1076_Z_BILLING_01", "polygon": [[0, 0], [960, 0], [960, 1080], [0, 1080]]}
      ]
    }
  }
}
